[
  {
    "key": "ctrl+j",
    "command": "workbench.action.quickOpenSelectNext",
    "when": "inQuickOpen"
  },
  {
    "key": "ctrl+k",
    "command": "workbench.action.quickOpenSelectPrevious",
    "when": "inQuickOpen"
  },
  {
    "key": "space space",
    "command": "workbench.action.quickOpen",
    "when": "editorTextFocus && vim.mode == 'Normal'"
  },
  {
    "key": "meta+s",
    "command": "workbench.action.files.save",
    "when": "isLinux"
  },
  // {
  //   "key": "meta+w",
  //   "command": "workbench.action.closeActiveEditor"
  // },
  // {
  //   "key": "meta+p",
  //   "command": "workbench.action.quickOpen"
  // },
  // {
  //   "key": "meta+i",
  //   "command": "github.copilot.inlineChat"
  // }
]